stickey/__init__.py
stickey/stickey.py
stickey-0.0.3.dist-info/METADATA
stickey-0.0.3.dist-info/WHEEL
stickey-0.0.3.dist-info/top_level.txt
stickey-0.0.3.dist-info/RECORD
