Metadata-Version: 2.1
Name: stickey
Version: 0.0.3
Summary: Make it stick is a package that allows user to upload pdf and take quick test created by AI.
Author: Kazuha
Classifier: Development Status :: 1 - Planning
Classifier: Intended Audience :: Developers
Classifier: Programming Language :: Python :: 3
Classifier: Operating System :: Unix
Classifier: Operating System :: MacOS :: MacOS X
Classifier: Operating System :: Microsoft :: Windows
